{
  "kind": "collectionType",
  "collectionName": "batch_signed_orders",
  "info": {
    "singularName": "batch-signed-order",
    "pluralName": "batch-signed-orders",
    "displayName": "BatchSignedOrder"
  },
  "options": {
    "draftAndPublish": true
  },
  "pluginOptions": {},
  "attributes": {
    "exchange_data": {
      "type": "text"
    },
    "exchange_user": {
      "type": "relation",
      "relation": "manyToOne",
      "target": "api::exchange-user.exchange-user",
      "inversedBy": "batch_signed_orders"
    },
    "orders": {
      "type": "relation",
      "relation": "oneToMany",
      "target": "api::order.order",
      "mappedBy": "batch_signed_order"
    }
  }
}
